Metadata-Version: 2.1
Name: keysafeQ
Version: 0.0.2
Summary: idk really bro
Home-page: 
Author: IRIS
Author-email: sr.pentesters@gmail.com
License: MIT
Keywords: keysafeQ
Classifier: Development Status :: 5 - Production/Stable
Classifier: Intended Audience :: Education
Classifier: Operating System :: Microsoft :: Windows :: Windows 10
Classifier: License :: OSI Approved :: MIT License
Classifier: Programming Language :: Python :: 3
License-File: LICENCE.txt
